metaphlantaxaprocessor/__about__.py
metaphlantaxaprocessor/__init__.py
metaphlantaxaprocessor/main.py
metaphlantaxaprocessor/process_rank.py
metaphlantaxaprocessor/utils.py
metaphlantaxaprocessor-0.0.3.dist-info/METADATA
metaphlantaxaprocessor-0.0.3.dist-info/WHEEL
metaphlantaxaprocessor-0.0.3.dist-info/entry_points.txt
metaphlantaxaprocessor-0.0.3.dist-info/licenses/LICENSE.txt
metaphlantaxaprocessor-0.0.3.dist-info/RECORD
