Metadata-Version: 2.4
Name: metaphlantaxaprocessor
Version: 0.0.3
Summary: MetaPhlAnTaxaProcessor is a Python-based utility designed to streamline the downstream analysis of MetaPhlAn output. It processes MetaPhlAn's taxonomic profiling data, converting it into structured CSV files for each taxonomic rank (e.g., Kingdom, Phyla, Class, etc.).
Project-URL: Documentation, https://github.com/vidyasagar0405/metaphlantaxaprocessor#readme
Project-URL: Issues, https://github.com/vidyasagar0405/metaphlantaxaprocessor/issues
Project-URL: Source, https://github.com/vidyasagar0405/metaphlantaxaprocessor
Author-email: vidyasagar0405 <vidyasagar0405@gmail.com>
License-Expression: MIT
License-File: LICENSE.txt
Classifier: Development Status :: 4 - Beta
Classifier: Programming Language :: Python
Classifier: Programming Language :: Python :: 3.7
Classifier: Programming Language :: Python :: 3.8
Classifier: Programming Language :: Python :: 3.9
Classifier: Programming Language :: Python :: 3.10
Classifier: Programming Language :: Python :: 3.11
Classifier: Programming Language :: Python :: 3.12
Classifier: Programming Language :: Python :: Implementation :: CPython
Classifier: Programming Language :: Python :: Implementation :: PyPy
Requires-Python: >=3.7
Requires-Dist: argparse
Requires-Dist: openpyxl
Requires-Dist: pandas
